atdataset/__init__.py
atdataset/atdataset.py
atdataset/feature.py
atdataset-0.1.2.dist-info/licenses/LICENSE
atdataset-0.1.2.dist-info/METADATA
atdataset-0.1.2.dist-info/WHEEL
atdataset-0.1.2.dist-info/top_level.txt
atdataset-0.1.2.dist-info/RECORD
