Metadata-Version: 2.4
Name: atdataset
Version: 0.1.2
Summary: Audio text dataset for PyTorch training based on webdataset.
Author: pkufool
License: Apache-2.0
Classifier: License :: OSI Approved :: Apache Software License
Classifier: Programming Language :: Python :: 3
Classifier: Programming Language :: Python :: 3 :: Only
Classifier: Programming Language :: Python :: 3.8
Classifier: Programming Language :: Python :: 3.9
Classifier: Programming Language :: Python :: 3.10
Classifier: Programming Language :: Python :: 3.11
Classifier: Programming Language :: Python :: 3.12
Classifier: Topic :: Scientific/Engineering :: Artificial Intelligence
Requires-Python: >=3.8
License-File: LICENSE
Requires-Dist: torch>=1.13
Requires-Dist: torchaudio>=0.13
Requires-Dist: webdataset>=0.2.86
Requires-Dist: soundfile>=0.13
Requires-Dist: numpy>=1.21
Dynamic: license-file
